{
  "required": true,
  "package": "net.beholderface.oneironaut.mixin",
  "compatibilityLevel": "JAVA_17",
  "refmap": "oneironaut-common-1.19.2-common-refmap.json",
  "minVersion": "0.8",
  "client": [
  ],
  "server": [
  ],
  "mixins": [
    "BlockRaycastImmunityMixin",
    "BrainsweepTargetMixin",
    "DecorativeWispMixin",
    "EntityRaycastImmunityMixin",
    "EraseSoulprintSignatureMixin",
    "IllegalIotasMixin",
    "ImpulseRedirectFireballMixin",
    "MiscWispMixin",
    "OpBreakBlockImmunityMixin",
    "QuietRodMixin",
    "SentinelTrapMixinCast",
    "SentinelTrapMixinSummon",
    "ShroudMediaCostMixin",
    "SlurryFrostWalkerMixin",
    "ZoneDistImmunityMixin"
  ],
  "injectors": {
    "defaultRequire": 1
  }
}